charon/__init__.py
charon/main.py
dante_charon-1.1.dist-info/DESCRIPTION.rst
dante_charon-1.1.dist-info/METADATA
dante_charon-1.1.dist-info/RECORD
dante_charon-1.1.dist-info/WHEEL
dante_charon-1.1.dist-info/entry_points.txt
dante_charon-1.1.dist-info/metadata.json
dante_charon-1.1.dist-info/top_level.txt
