Metadata-Version: 2.0
Name: dante-charon
Version: 1.1
Summary: Prepare interface to monitor and increase power and set normal managed mode
Home-page: https://github.com/DanteOnline/charon
Author: DanteOnline
Author-email: iamdanteonline@gmail.com
License: GNU General Public License v3.0
Keywords: iw,dev,trxpower,monitor,managed,interface,wi-fi
Platform: UNKNOWN
